{
  "recipes": [
    {
      "name": "Sticky Toffee Pudding",
      "author": "They call me M",
      "country": "United Kingdom",
      "description": "Delicious post-supper treat",
      "image": "https://www.wearesovegan.com/wp-content/uploads/2021/09/veganultimatestickytoffeepuddingrecipeh1.jpg",
      "ingredients": [
        {
          "id": 1,
          "ingredient": "flour",
          "quantity": "lots"
        }
      ],
      "instructions": "Boil 'em, mash 'em stick 'em in a stew",
      "flagURL": "https://flagcdn.com/w320/gb.png",
      "id": 2
    },
    {
      "name": "Greek Salad",
      "author": "Gorgeous Georgios",
      "country": "Greece",
      "description": "The cornerstone of my diet",
      "image": "https://www.simplyrecipes.com/thmb/au60mVTA5EPLLknjdtQ9BYO0OC4=/1067x1067/smart/filters:no_upscale()/__opt__aboutcom__coeus__resources__content_migration__simply_recipes__uploads__2011__08__dads-greek-salad-horiz-a-1600-bc71b85bc907414a9bb3179a923b58fc.jpg",
      "ingredients": [
        {
          "id": 1,
          "ingredient": "olive oil",
          "quantity": "1 l"
        }
      ],
      "instructions": "mix all ingredients and serve immediately",
      "flagURL": "https://flagcdn.com/w320/gr.png",
      "id": 3
    },
    {
      "name": "Lefse ",
      "author": "Gunnar",
      "country": "Norway",
      "description": "Norwegian Potato Flatbread ",
      "image": "https://images.food52.com/JUnhZov2ixqSvYZqlcr68Gq_vis=/1200x900/f31cfc5d-a4c9-4e83-ba17-b40cc739643f--lefse_bfast_1.jpg",
      "ingredients": [
        {
          "id": 1,
          "ingredient": "potatoes (peeled and cooked)",
          "quantity": "269g (or 1 3/4 cups)"
        },
        {
          "id": 2,
          "ingredient": "all-purpose flour ",
          "quantity": "53"
        },
        {
          "id": 3,
          "ingredient": "butter",
          "quantity": "2 tbs"
        },
        {
          "id": 4,
          "ingredient": "milk or heavy cream",
          "quantity": "2 tbs"
        },
        {
          "id": 5,
          "ingredient": "salt",
          "quantity": "1 tsp"
        },
        {
          "id": 6,
          "ingredient": "granulated sugar",
          "quantity": "1 tsp"
        }
      ],
      "instructions": "Divide the dough into 12 pieces.\nGently roll it into a ball, then place it on a well-floured work surface. Pat into a circle.\n\nPlace the lefse onto the griddle or into the skillet. Cook on one side until speckled with brown spots; this should take about a minute. Flip and repeat.\n\nServe warm or at room temperature, spread with softened butter and rolled into a cylinder or folded into quarters. Add sugar or cinnamon sugar for a sweet treat.\n\n",
      "flagURL": "https://flagcdn.com/w320/no.png",
      "id": 4
    },
    {
      "name": "Sticky Toffee Pudding",
      "author": "They call me M",
      "country": "Antarctica",
      "description": "Delicious post-supper treat",
      "image": "https://www.wearesovegan.com/wp-content/uploads/2021/09/veganultimatestickytoffeepuddingrecipeh1.jpg",
      "ingredients": [
        {
          "id": 1,
          "ingredient": "flour",
          "quantity": "1 l"
        }
      ],
      "instructions": "nhjfjfj",
      "flagURL": "https://flagcdn.com/w320/aq.png",
      "id": 5
    },
    {
      "name": "Sticky Toffee Pudding",
      "author": "They call me M",
      "country": "Antarctica",
      "description": "Delicious post-supper treat",
      "image": "https://www.simplyrecipes.com/thmb/au60mVTA5EPLLknjdtQ9BYO0OC4=/1067x1067/smart/filters:no_upscale()/__opt__aboutcom__coeus__resources__content_migration__simply_recipes__uploads__2011__08__dads-greek-salad-horiz-a-1600-bc71b85bc907414a9bb3179a923b58fc.jpg",
      "ingredients": [
        {
          "id": 1,
          "ingredient": "flour",
          "quantity": "lots"
        },
        {
          "id": 2,
          "ingredient": "olive oil",
          "quantity": "1 l"
        }
      ],
      "instructions": "bhadhdhadf",
      "flagURL": "https://flagcdn.com/w320/aq.png",
      "id": 6
    },
    {
      "name": "Sticky Toffee Pudding",
      "author": "They call me M",
      "country": "Argentina",
      "description": "Delicious post-supper treat",
      "image": "https://www.wearesovegan.com/wp-content/uploads/2021/09/veganultimatestickytoffeepuddingrecipeh1.jpg",
      "ingredients": [
        {
          "id": 1,
          "ingredient": "flour",
          "quantity": "lots"
        },
        {
          "id": 2,
          "ingredient": "olive oil",
          "quantity": "269g (or 1 3/4 cups)"
        }
      ],
      "instructions": "shhfhsf",
      "flagURL": "https://flagcdn.com/w320/ar.png",
      "id": 7
    },
    {
      "name": "Sticky Toffee Pudding",
      "author": "James Bond",
      "country": "Azerbaijan",
      "description": "The cornerstone of my diet\"",
      "image": "https://images.food52.com/JUnhZov2ixqSvYZqlcr68Gq_vis=/1200x900/f31cfc5d-a4c9-4e83-ba17-b40cc739643f--lefse_bfast_1.jpg",
      "ingredients": [
        {
          "id": 1,
          "ingredient": "flour",
          "quantity": "lots"
        },
        {
          "id": 2,
          "ingredient": "olive oil",
          "quantity": "lots"
        }
      ],
      "instructions": "nvj,hvjhvhv,j",
      "flagURL": "https://flagcdn.com/w320/az.png",
      "id": 8
    },
    {
      "name": "Sticky Toffee Pudding",
      "author": "They call me M",
      "country": "Åland Islands",
      "description": "Delicious post-supper treat",
      "image": "https://www.wearesovegan.com/wp-content/uploads/2021/09/veganultimatestickytoffeepuddingrecipeh1.jpg",
      "ingredients": [
        {
          "id": 1,
          "ingredient": "flour",
          "quantity": "lots"
        },
        {
          "id": 2,
          "ingredient": "olive oil",
          "quantity": "1 l"
        }
      ],
      "instructions": "fdhfdhfd",
      "flagURL": "https://flagcdn.com/w320/ax.png",
      "id": 9
    }
  ]
}